broadcaster/__init__.py
broadcaster/_base.py
broadcaster/py.typed
broadcaster/_backends/__init__.py
broadcaster/_backends/base.py
broadcaster/_backends/kafka.py
broadcaster/_backends/memory.py
broadcaster/_backends/postgres.py
broadcaster/_backends/redis.py
permit_broadcaster-0.2.5.dist-info/LICENSE.md
permit_broadcaster-0.2.5.dist-info/METADATA
permit_broadcaster-0.2.5.dist-info/WHEEL
permit_broadcaster-0.2.5.dist-info/top_level.txt
permit_broadcaster-0.2.5.dist-info/RECORD
