Metadata-Version: 2.1
Name: permit-broadcaster
Version: 0.2.5
Summary: Simple broadcast channels (Permit fork)
Home-page: https://github.com/permitio/broadcaster
Author: Tom Christie
Author-email: tom@tomchristie.com
License: BSD
Classifier: Development Status :: 3 - Alpha
Classifier: Environment :: Web Environment
Classifier: Intended Audience :: Developers
Classifier: License :: OSI Approved :: BSD License
Classifier: Operating System :: OS Independent
Classifier: Topic :: Internet :: WWW/HTTP
Classifier: Programming Language :: Python :: 3
Classifier: Programming Language :: Python :: 3.8
Classifier: Programming Language :: Python :: 3.9
Classifier: Programming Language :: Python :: 3.10
Classifier: Programming Language :: Python :: 3.11
Requires-Python: >=3.8
License-File: LICENSE.md
Provides-Extra: kafka
Requires-Dist: aiokafka ; extra == 'kafka'
Provides-Extra: postgres
Requires-Dist: asyncpg ; extra == 'postgres'
Provides-Extra: redis
Requires-Dist: asyncio-redis ; extra == 'redis'
Provides-Extra: test
Requires-Dist: pytest ; extra == 'test'
Requires-Dist: pytest-asyncio ; extra == 'test'
